pythumbnail/__init__.py
pythumbnail/parsing.py
pythumbnail/rulegroup.py
pythumbnail/thumbnail.py
pythumbnail-0.0.9.dist-info/LICENSE
pythumbnail-0.0.9.dist-info/METADATA
pythumbnail-0.0.9.dist-info/WHEEL
pythumbnail-0.0.9.dist-info/top_level.txt
pythumbnail-0.0.9.dist-info/RECORD
