Metadata-Version: 2.1
Name: pythumbnail
Version: 0.0.9
Summary: A quick thumbnail creator for python codes
Home-page: https://github.com/kevinyang372/py-thumbnail
Author: Yunfan Yang
Author-email: yunfan.yang@minerva.kgi.edu
License: Apache2
Platform: UNKNOWN
Classifier: Development Status :: 4 - Beta
Classifier: Intended Audience :: System Administrators
Classifier: License :: OSI Approved :: Apache Software License
Classifier: Programming Language :: Python :: 3
